Himanshu/_init_.py
JARVIS_STT-0.1.dist-info/METADATA
JARVIS_STT-0.1.dist-info/WHEEL
JARVIS_STT-0.1.dist-info/top_level.txt
JARVIS_STT-0.1.dist-info/RECORD
