Metadata-Version: 2.1
Name: JARVIS-STT
Version: 0.1
Summary: This is speech to text package
Author: Genius
Author-email: amarjeetshah93@gmail.com
